[{"OldBuildArtifact":"android.arch.core:common","AndroidXBuildArtifact":"androidx.arch.core:core-common:2.0.0-rc01","id":0},{"OldBuildArtifact":"android.arch.core:core","AndroidXBuildArtifact":"androidx.arch.core:core:2.0.0-rc01","id":1},{"OldBuildArtifact":"android.arch.core:core-testing","AndroidXBuildArtifact":"androidx.arch.core:core-testing:2.0.0-rc01","id":2},{"OldBuildArtifact":"android.arch.core:runtime","AndroidXBuildArtifact":"androidx.arch.core:core-runtime:2.0.0-rc01","id":3},{"OldBuildArtifact":"android.arch.lifecycle:common","AndroidXBuildArtifact":"androidx.lifecycle:lifecycle-common:2.0.0-rc01","id":4},{"OldBuildArtifact":"android.arch.lifecycle:common-java8","AndroidXBuildArtifact":"androidx.lifecycle:lifecycle-common-java8:2.0.0-rc01","id":5},{"OldBuildArtifact":"android.arch.lifecycle:compiler","AndroidXBuildArtifact":"androidx.lifecycle:lifecycle-compiler:2.0.0-rc01","id":6},{"OldBuildArtifact":"android.arch.lifecycle:extensions","AndroidXBuildArtifact":"androidx.lifecycle:lifecycle-extensions:2.0.0-rc01","id":7},{"OldBuildArtifact":"android.arch.lifecycle:livedata","AndroidXBuildArtifact":"androidx.lifecycle:lifecycle-livedata:2.0.0-rc01","id":8},{"OldBuildArtifact":"android.arch.lifecycle:livedata-core","AndroidXBuildArtifact":"androidx.lifecycle:lifecycle-livedata-core:2.0.0-rc01","id":9},{"OldBuildArtifact":"android.arch.lifecycle:reactivestreams","AndroidXBuildArtifact":"androidx.lifecycle:lifecycle-reactivestreams:2.0.0-rc01","id":10},{"OldBuildArtifact":"android.arch.lifecycle:runtime","AndroidXBuildArtifact":"androidx.lifecycle:lifecycle-runtime:2.0.0-rc01","id":11},{"OldBuildArtifact":"android.arch.lifecycle:viewmodel","AndroidXBuildArtifact":"androidx.lifecycle:lifecycle-viewmodel:2.0.0-rc01","id":12},{"OldBuildArtifact":"android.arch.paging:common","AndroidXBuildArtifact":"androidx.paging:paging-common:2.0.0-rc01","id":13},{"OldBuildArtifact":"android.arch.paging:runtime","AndroidXBuildArtifact":"androidx.paging:paging-runtime:2.0.0-rc01","id":14},{"OldBuildArtifact":"android.arch.paging:rxjava2","AndroidXBuildArtifact":"androidx.paging:paging-rxjava2:2.0.0-rc01","id":15},{"OldBuildArtifact":"android.arch.persistence.room:common","AndroidXBuildArtifact":"androidx.room:room-common:2.0.0-rc01","id":16},{"OldBuildArtifact":"android.arch.persistence.room:compiler","AndroidXBuildArtifact":"androidx.room:room-compiler:2.0.0-rc01","id":17},{"OldBuildArtifact":"android.arch.persistence.room:guava","AndroidXBuildArtifact":"androidx.room:room-guava:2.0.0-rc01","id":18},{"OldBuildArtifact":"android.arch.persistence.room:migration","AndroidXBuildArtifact":"androidx.room:room-migration:2.0.0-rc01","id":19},{"OldBuildArtifact":"android.arch.persistence.room:runtime","AndroidXBuildArtifact":"androidx.room:room-runtime:2.0.0-rc01","id":20},{"OldBuildArtifact":"android.arch.persistence.room:rxjava2","AndroidXBuildArtifact":"androidx.room:room-rxjava2:2.0.0-rc01","id":21},{"OldBuildArtifact":"android.arch.persistence.room:testing","AndroidXBuildArtifact":"androidx.room:room-testing:2.0.0-rc01","id":22},{"OldBuildArtifact":"android.arch.persistence:db","AndroidXBuildArtifact":"androidx.sqlite:sqlite:2.0.0-rc01","id":23},{"OldBuildArtifact":"android.arch.persistence:db-framework","AndroidXBuildArtifact":"androidx.sqlite:sqlite-framework:2.0.0-rc01","id":24},{"OldBuildArtifact":"com.android.support.constraint:constraint-layout","AndroidXBuildArtifact":"androidx.constraintlayout:constraintlayout:1.1.2","id":25},{"OldBuildArtifact":"com.android.support.constraint:constraint-layout-solver","AndroidXBuildArtifact":"androidx.constraintlayout:constraintlayout-solver:1.1.2","id":26},{"OldBuildArtifact":"com.android.support.test.espresso.idling:idling-concurrent","AndroidXBuildArtifact":"androidx.test.espresso.idling:idling-concurrent:3.1.0","id":27},{"OldBuildArtifact":"com.android.support.test.espresso.idling:idling-net","AndroidXBuildArtifact":"androidx.test.espresso.idling:idling-net:3.1.0","id":28},{"OldBuildArtifact":"com.android.support.test.espresso:espresso-accessibility","AndroidXBuildArtifact":"androidx.test.espresso:espresso-accessibility:3.1.0","id":29},{"OldBuildArtifact":"com.android.support.test.espresso:espresso-contrib","AndroidXBuildArtifact":"androidx.test.espresso:espresso-contrib:3.1.0","id":30},{"OldBuildArtifact":"com.android.support.test.espresso:espresso-core","AndroidXBuildArtifact":"androidx.test.espresso:espresso-core:3.1.0","id":31},{"OldBuildArtifact":"com.android.support.test.espresso:espresso-idling-resource","AndroidXBuildArtifact":"androidx.test.espresso:espresso-idling-resource:3.1.0","id":32},{"OldBuildArtifact":"com.android.support.test.espresso:espresso-intents","AndroidXBuildArtifact":"androidx.test.espresso:espresso-intents:3.1.0","id":33},{"OldBuildArtifact":"com.android.support.test.espresso:espresso-remote","AndroidXBuildArtifact":"androidx.test.espresso:espresso-remote:3.1.0","id":34},{"OldBuildArtifact":"com.android.support.test.espresso:espresso-web","AndroidXBuildArtifact":"androidx.test.espresso:espresso-web:3.1.0","id":35},{"OldBuildArtifact":"com.android.support.test.janktesthelper:janktesthelper","AndroidXBuildArtifact":"androidx.test.jank:janktesthelper:1.0.1","id":36},{"OldBuildArtifact":"com.android.support.test.services:test-services","AndroidXBuildArtifact":"androidx.test:test-services:1.1.0","id":37},{"OldBuildArtifact":"com.android.support.test.uiautomator:uiautomator","AndroidXBuildArtifact":"androidx.test.uiautomator:uiautomator:2.2.0","id":38},{"OldBuildArtifact":"com.android.support.test:monitor","AndroidXBuildArtifact":"androidx.test:monitor:1.1.0","id":39},{"OldBuildArtifact":"com.android.support.test:orchestrator","AndroidXBuildArtifact":"androidx.test:orchestrator:1.1.0","id":40},{"OldBuildArtifact":"com.android.support.test:rules","AndroidXBuildArtifact":"androidx.test:rules:1.1.0","id":41},{"OldBuildArtifact":"com.android.support.test:runner","AndroidXBuildArtifact":"androidx.test:runner:1.1.0","id":42},{"OldBuildArtifact":"com.android.support:animated-vector-drawable","AndroidXBuildArtifact":"androidx.vectordrawable:vectordrawable-animated:1.0.0","id":43},{"OldBuildArtifact":"com.android.support:appcompat-v7","AndroidXBuildArtifact":"androidx.appcompat:appcompat:1.0.0","id":44},{"OldBuildArtifact":"com.android.support:asynclayoutinflater","AndroidXBuildArtifact":"androidx.asynclayoutinflater:asynclayoutinflater:1.0.0","id":45},{"OldBuildArtifact":"com.android.support:car","AndroidXBuildArtifact":"androidx.car:car:1.0.0-alpha5","id":46},{"OldBuildArtifact":"com.android.support:cardview-v7","AndroidXBuildArtifact":"androidx.cardview:cardview:1.0.0","id":47},{"OldBuildArtifact":"com.android.support:collections","AndroidXBuildArtifact":"androidx.collection:collection:1.0.0","id":48},{"OldBuildArtifact":"com.android.support:coordinatorlayout","AndroidXBuildArtifact":"androidx.coordinatorlayout:coordinatorlayout:1.0.0","id":49},{"OldBuildArtifact":"com.android.support:cursoradapter","AndroidXBuildArtifact":"androidx.cursoradapter:cursoradapter:1.0.0","id":50},{"OldBuildArtifact":"com.android.support:customtabs","AndroidXBuildArtifact":"androidx.browser:browser:1.0.0","id":51},{"OldBuildArtifact":"com.android.support:customview","AndroidXBuildArtifact":"androidx.customview:customview:1.0.0","id":52},{"OldBuildArtifact":"com.android.support:design","AndroidXBuildArtifact":"com.google.android.material:material:1.0.0-rc01","id":53},{"OldBuildArtifact":"com.android.support:documentfile","AndroidXBuildArtifact":"androidx.documentfile:documentfile:1.0.0","id":54},{"OldBuildArtifact":"com.android.support:drawerlayout","AndroidXBuildArtifact":"androidx.drawerlayout:drawerlayout:1.0.0","id":55},{"OldBuildArtifact":"com.android.support:exifinterface","AndroidXBuildArtifact":"androidx.exifinterface:exifinterface:1.0.0","id":56},{"OldBuildArtifact":"com.android.support:gridlayout-v7","AndroidXBuildArtifact":"androidx.gridlayout:gridlayout:1.0.0","id":57},{"OldBuildArtifact":"com.android.support:heifwriter","AndroidXBuildArtifact":"androidx.heifwriter:heifwriter:1.0.0","id":58},{"OldBuildArtifact":"com.android.support:interpolator","AndroidXBuildArtifact":"androidx.interpolator:interpolator:1.0.0","id":59},{"OldBuildArtifact":"com.android.support:leanback-v17","AndroidXBuildArtifact":"androidx.leanback:leanback:1.0.0","id":60},{"OldBuildArtifact":"com.android.support:loader","AndroidXBuildArtifact":"androidx.loader:loader:1.0.0","id":61},{"OldBuildArtifact":"com.android.support:localbroadcastmanager","AndroidXBuildArtifact":"androidx.localbroadcastmanager:localbroadcastmanager:1.0.0","id":62},{"OldBuildArtifact":"com.android.support:media2","AndroidXBuildArtifact":"androidx.media2:media2:1.0.0-alpha03","id":63},{"OldBuildArtifact":"com.android.support:media2-exoplayer","AndroidXBuildArtifact":"androidx.media2:media2-exoplayer:1.0.0-alpha01","id":64},{"OldBuildArtifact":"com.android.support:mediarouter-v7","AndroidXBuildArtifact":"androidx.mediarouter:mediarouter:1.0.0","id":65},{"OldBuildArtifact":"com.android.support:multidex","AndroidXBuildArtifact":"androidx.multidex:multidex:2.0.0","id":66},{"OldBuildArtifact":"com.android.support:multidex-instrumentation","AndroidXBuildArtifact":"androidx.multidex:multidex-instrumentation:2.0.0","id":67},{"OldBuildArtifact":"com.android.support:palette-v7","AndroidXBuildArtifact":"androidx.palette:palette:1.0.0","id":68},{"OldBuildArtifact":"com.android.support:percent","AndroidXBuildArtifact":"androidx.percentlayout:percentlayout:1.0.0","id":69},{"OldBuildArtifact":"com.android.support:preference-leanback-v17","AndroidXBuildArtifact":"androidx.leanback:leanback-preference:1.0.0","id":70},{"OldBuildArtifact":"com.android.support:preference-v14","AndroidXBuildArtifact":"androidx.legacy:legacy-preference-v14:1.0.0","id":71},{"OldBuildArtifact":"com.android.support:preference-v7","AndroidXBuildArtifact":"androidx.preference:preference:1.0.0","id":72},{"OldBuildArtifact":"com.android.support:print","AndroidXBuildArtifact":"androidx.print:print:1.0.0","id":73},{"OldBuildArtifact":"com.android.support:recommendation","AndroidXBuildArtifact":"androidx.recommendation:recommendation:1.0.0","id":74},{"OldBuildArtifact":"com.android.support:recyclerview-selection","AndroidXBuildArtifact":"androidx.recyclerview:recyclerview-selection:1.0.0","id":75},{"OldBuildArtifact":"com.android.support:recyclerview-v7","AndroidXBuildArtifact":"androidx.recyclerview:recyclerview:1.0.0","id":76},{"OldBuildArtifact":"com.android.support:slices-builders","AndroidXBuildArtifact":"androidx.slice:slice-builders:1.0.0","id":77},{"OldBuildArtifact":"com.android.support:slices-core","AndroidXBuildArtifact":"androidx.slice:slice-core:1.0.0","id":78},{"OldBuildArtifact":"com.android.support:slices-view","AndroidXBuildArtifact":"androidx.slice:slice-view:1.0.0","id":79},{"OldBuildArtifact":"com.android.support:slidingpanelayout","AndroidXBuildArtifact":"androidx.slidingpanelayout:slidingpanelayout:1.0.0","id":80},{"OldBuildArtifact":"com.android.support:support-annotations","AndroidXBuildArtifact":"androidx.annotation:annotation:1.0.0","id":81},{"OldBuildArtifact":"com.android.support:support-compat","AndroidXBuildArtifact":"androidx.core:core:1.0.0","id":82},{"OldBuildArtifact":"com.android.support:support-content","AndroidXBuildArtifact":"androidx.contentpager:contentpager:1.0.0","id":83},{"OldBuildArtifact":"com.android.support:support-core-ui","AndroidXBuildArtifact":"androidx.legacy:legacy-support-core-ui:1.0.0","id":84},{"OldBuildArtifact":"com.android.support:support-core-utils","AndroidXBuildArtifact":"androidx.legacy:legacy-support-core-utils:1.0.0","id":85},{"OldBuildArtifact":"com.android.support:support-dynamic-animation","AndroidXBuildArtifact":"androidx.dynamicanimation:dynamicanimation:1.0.0","id":86},{"OldBuildArtifact":"com.android.support:support-emoji","AndroidXBuildArtifact":"androidx.emoji:emoji:1.0.0","id":87},{"OldBuildArtifact":"com.android.support:support-emoji-appcompat","AndroidXBuildArtifact":"androidx.emoji:emoji-appcompat:1.0.0","id":88},{"OldBuildArtifact":"com.android.support:support-emoji-bundled","AndroidXBuildArtifact":"androidx.emoji:emoji-bundled:1.0.0","id":89},{"OldBuildArtifact":"com.android.support:support-fragment","AndroidXBuildArtifact":"androidx.fragment:fragment:1.0.0","id":90},{"OldBuildArtifact":"com.android.support:support-media-compat","AndroidXBuildArtifact":"androidx.media:media:1.0.0","id":91},{"OldBuildArtifact":"com.android.support:support-tv-provider","AndroidXBuildArtifact":"androidx.tvprovider:tvprovider:1.0.0","id":92},{"OldBuildArtifact":"com.android.support:support-v13","AndroidXBuildArtifact":"androidx.legacy:legacy-support-v13:1.0.0","id":93},{"OldBuildArtifact":"com.android.support:support-v4","AndroidXBuildArtifact":"androidx.legacy:legacy-support-v4:1.0.0","id":94},{"OldBuildArtifact":"com.android.support:support-vector-drawable","AndroidXBuildArtifact":"androidx.vectordrawable:vectordrawable:1.0.0","id":95},{"OldBuildArtifact":"com.android.support:swiperefreshlayout","AndroidXBuildArtifact":"androidx.swiperefreshlayout:swiperefreshlayout:1.0.0","id":96},{"OldBuildArtifact":"com.android.support:textclassifier","AndroidXBuildArtifact":"androidx.textclassifier:textclassifier:1.0.0","id":97},{"OldBuildArtifact":"com.android.support:transition","AndroidXBuildArtifact":"androidx.transition:transition:1.0.0","id":98},{"OldBuildArtifact":"com.android.support:versionedparcelable","AndroidXBuildArtifact":"androidx.versionedparcelable:versionedparcelable:1.0.0","id":99},{"OldBuildArtifact":"com.android.support:viewpager","AndroidXBuildArtifact":"androidx.viewpager:viewpager:1.0.0","id":100},{"OldBuildArtifact":"com.android.support:wear","AndroidXBuildArtifact":"androidx.wear:wear:1.0.0","id":101},{"OldBuildArtifact":"com.android.support:webkit","AndroidXBuildArtifact":"androidx.webkit:webkit:1.0.0","id":102}]